reach_commons/__init__.py
reach_commons/app_logging/__init__.py
reach_commons/app_logging/http_logger.py
reach_commons/app_logging/log_deprecated_endpoints.py
reach_commons/app_logging/logger.py
reach_commons/app_logging/logging_config.py
reach_commons/app_logging/logging_utils.py
reach_commons/clients/__init__.py
reach_commons/clients/event_processor.py
reach_commons/clients/hubspot.py
reach_commons/clients/outscraper.py
reach_commons/clients/reach_data_bridge.py
reach_commons/clients/reach_ops_api.py
reach_commons/mongo/__init__.py
reach_commons/mongo/customer_persistence.py
reach_commons/mongo/customer_persistence_async.py
reach_commons/mongo/validation/__init__.py
reach_commons/reach_aws/__init__.py
reach_commons/reach_aws/commons.py
reach_commons/reach_aws/db_config.py
reach_commons/reach_aws/dynamo_db.py
reach_commons/reach_aws/exceptions.py
reach_commons/reach_aws/firehose.py
reach_commons/reach_aws/kms.py
reach_commons/reach_aws/reach_rate_limiter.py
reach_commons/reach_aws/s3.py
reach_commons/reach_aws/sqs.py
reach_commons/reach_base_model.py
reach_commons/redis_manager.py
reach_commons/sms_smart_encoding.py
reach_commons/utils.py
reach_commons/validations.py
reach_commons-0.18.42.dist-info/METADATA
reach_commons-0.18.42.dist-info/WHEEL
reach_commons-0.18.42.dist-info/RECORD
