Metadata-Version: 2.1
Name: reach_commons
Version: 0.18.42
Summary: Reach Commons is a versatile utility library designed to streamline and enhance development workflows within the Reach ecosystem.
License: MIT
Author: Engineering
Author-email: engineering@getreach.ai
Requires-Python: >=3.8,<4.0
Classifier: License :: OSI Approved :: MIT License
Classifier: Operating System :: OS Independent
Classifier: Programming Language :: Python :: 3
Classifier: Programming Language :: Python :: 3.8
Classifier: Programming Language :: Python :: 3.9
Classifier: Programming Language :: Python :: 3.10
Classifier: Programming Language :: Python :: 3.11
Classifier: Programming Language :: Python :: 3.12
Requires-Dist: curlify (==3.0.0)
Requires-Dist: fastapi (>=0.115.5)
Requires-Dist: pydantic (>=2.9.2)
Requires-Dist: setuptools (==70.0.0)
Requires-Dist: twine (==4.0.2)
Requires-Dist: wheel (==0.41.2)
